BagelDB.py
bageldb_beta-0.1.0.dist-info/LICENSE.txt
bageldb_beta-0.1.0.dist-info/METADATA
bageldb_beta-0.1.0.dist-info/WHEEL
bageldb_beta-0.1.0.dist-info/top_level.txt
bageldb_beta-0.1.0.dist-info/RECORD
