Metadata-Version: 2.1
Name: bageldb-beta
Version: 0.1.0
Summary: BagelDB is a Python library for interacting with the BagelDB API.
Home-page: https://github.com/Bagel-DB/Client
Author: Bidhan Roy
Author-email: bidhan@bageldb.ai
Classifier: Development Status :: 3 - Alpha
Classifier: Intended Audience :: Developers
Classifier: License :: OSI Approved :: MIT License
Classifier: Programming Language :: Python :: 3
Classifier: Programming Language :: Python :: 3.7
Classifier: Programming Language :: Python :: 3.8
Classifier: Programming Language :: Python :: 3.9
License-File: LICENSE.txt
Requires-Dist: requests
